{
  "candidate_id": "P5_H08_enigma_H08_compound",
  "spec_name": "enigma_H08_compound",
  "valid": true,
  "failure_type": null,
  "eval_time_s": 1.6265850169875193,
  "final_validation_bpb": 2.253388678846014,
  "best_validation_bpb": 2.253388678846014,
  "tokens_per_sec": 38603.71712091908,
  "mean_step_time_ms": 26.525943001615815,
  "stability_penalty": 0.0,
  "memory_bytes": 939936320,
  "grad_norm_spikes": 0,
  "nan_failures": 0,
  "inf_failures": 0,
  "curve": [
    {
      "step": 1,
      "train_bpb": 15.202106485274864,
      "val_bpb": null,
      "tokens_seen": 1024
    },
    {
      "step": 2,
      "train_bpb": 14.895480680843374,
      "val_bpb": null,
      "tokens_seen": 2048
    },
    {
      "step": 3,
      "train_bpb": 14.523337741600393,
      "val_bpb": null,
      "tokens_seen": 3072
    },
    {
      "step": 4,
      "train_bpb": 13.666959074726883,
      "val_bpb": null,
      "tokens_seen": 4096
    },
    {
      "step": 5,
      "train_bpb": 13.07644494816917,
      "val_bpb": null,
      "tokens_seen": 5120
    },
    {
      "step": 6,
      "train_bpb": 14.105309831107217,
      "val_bpb": null,
      "tokens_seen": 6144
    },
    {
      "step": 7,
      "train_bpb": 13.133589967536658,
      "val_bpb": null,
      "tokens_seen": 7168
    },
    {
      "step": 8,
      "train_bpb": 12.852923912357003,
      "val_bpb": null,
      "tokens_seen": 8192
    },
    {
      "step": 9,
      "train_bpb": 12.58386324645757,
      "val_bpb": null,
      "tokens_seen": 9216
    },
    {
      "step": 10,
      "train_bpb": 12.945654205979816,
      "val_bpb": 2.3884538678382263,
      "tokens_seen": 10240
    },
    {
      "step": 11,
      "train_bpb": 11.951514684042781,
      "val_bpb": null,
      "tokens_seen": 11264
    },
    {
      "step": 12,
      "train_bpb": 12.274579278174343,
      "val_bpb": null,
      "tokens_seen": 12288
    },
    {
      "step": 13,
      "train_bpb": 11.725364377464222,
      "val_bpb": null,
      "tokens_seen": 13312
    },
    {
      "step": 14,
      "train_bpb": 11.598801656763678,
      "val_bpb": null,
      "tokens_seen": 14336
    },
    {
      "step": 15,
      "train_bpb": 11.948427251494492,
      "val_bpb": null,
      "tokens_seen": 15360
    },
    {
      "step": 16,
      "train_bpb": 11.919385573139195,
      "val_bpb": null,
      "tokens_seen": 16384
    },
    {
      "step": 17,
      "train_bpb": 11.568543717101479,
      "val_bpb": null,
      "tokens_seen": 17408
    },
    {
      "step": 18,
      "train_bpb": 11.851759243097524,
      "val_bpb": null,
      "tokens_seen": 18432
    },
    {
      "step": 19,
      "train_bpb": 11.629450341008637,
      "val_bpb": null,
      "tokens_seen": 19456
    },
    {
      "step": 20,
      "train_bpb": 11.796365695046424,
      "val_bpb": 2.253388678846014,
      "tokens_seen": 20480
    }
  ],
  "telemetry": [
    {
      "step": 1,
      "loss": 10.537297248840332,
      "grad_norm": 1.8570659060544834,
      "gate_value": 1.0,
      "update_multiplier": 1.0,
      "trust_ratio_mix": 1.0,
      "clip_threshold": null,
      "beta2_override": null,
      "orthogonal_mix": 1.0,
      "loss_ema": 10.537297248840332,
      "loss_improvement_ema": 0.0,
      "grad_norm_ema": 0.0,
      "update_ratio_ema": 0.0,
      "grad_alignment_ema": 0.0,
      "step_fraction": 0.05,
      "mean_update_param_ratio": 1.0020901560783386,
      "max_update_param_ratio": 1.0031447410583496,
      "mean_trust_ratio": 0.821317046880722
    },
    {
      "step": 2,
      "loss": 10.324760437011719,
      "grad_norm": 1.2921747665886956,
      "gate_value": 1.0,
      "update_multiplier": 1.0,
      "trust_ratio_mix": 1.0,
      "clip_threshold": null,
      "beta2_override": null,
      "orthogonal_mix": 1.0,
      "loss_ema": 10.516043567657471,
      "loss_improvement_ema": 0.002125368118286097,
      "grad_norm_ema": 0.0,
      "update_ratio_ema": 0.0,
      "grad_alignment_ema": 0.0,
      "step_fraction": 0.1,
      "mean_update_param_ratio": 1.0014801025390625,
      "max_update_param_ratio": 1.0017497539520264,
      "mean_trust_ratio": 0.7449877113103867
    },
    {
      "step": 3,
      "loss": 10.066810607910156,
      "grad_norm": 1.714132071503318,
      "gate_value": 1.0,
      "update_multiplier": 1.0,
      "trust_ratio_mix": 1.0,
      "clip_threshold": null,
      "beta2_override": null,
      "orthogonal_mix": 1.0,
      "loss_ema": 10.47112027168274,
      "loss_improvement_ema": 0.006405160903930652,
      "grad_norm_ema": 0.0,
      "update_ratio_ema": 0.0,
      "grad_alignment_ema": 0.0,
      "step_fraction": 0.15,
      "mean_update_param_ratio": 1.0010980069637299,
      "max_update_param_ratio": 1.0015212297439575,
      "mean_trust_ratio": 0.7271296381950378
    },
    {
      "step": 4,
      "loss": 9.473214149475098,
      "grad_norm": 3.8445543372859787,
      "gate_value": 1.0,
      "update_multiplier": 1.0,
      "trust_ratio_mix": 1.0,
      "clip_threshold": null,
      "beta2_override": null,
      "orthogonal_mix": 1.0,
      "loss_ema": 10.371329659461976,
      "loss_improvement_ema": 0.01574370603561393,
      "grad_norm_ema": 0.0,
      "update_ratio_ema": 0.0,
      "grad_alignment_ema": 0.0,
      "step_fraction": 0.2,
      "mean_update_param_ratio": 1.0008257627487183,
      "max_update_param_ratio": 1.0014867782592773,
      "mean_trust_ratio": 0.7354218363761902
    },
    {
      "step": 5,
      "loss": 9.0639009475708,
      "grad_norm": 6.0687942985455186,
      "gate_value": 1.0,
      "update_multiplier": 1.0,
      "trust_ratio_mix": 1.0,
      "clip_threshold": null,
      "beta2_override": null,
      "orthogonal_mix": 1.0,
      "loss_ema": 10.240586788272859,
      "loss_improvement_ema": 0.027243622550964235,
      "grad_norm_ema": 0.0,
      "update_ratio_ema": 0.0,
      "grad_alignment_ema": 0.0,
      "step_fraction": 0.25,
      "mean_update_param_ratio": 1.0007204860448837,
      "max_update_param_ratio": 1.001323938369751,
      "mean_trust_ratio": 0.7480724155902863
    },
    {
      "step": 6,
      "loss": 9.777055740356445,
      "grad_norm": 4.375323849885337,
      "gate_value": 1.0,
      "update_multiplier": 1.0,
      "trust_ratio_mix": 1.0,
      "clip_threshold": null,
      "beta2_override": null,
      "orthogonal_mix": 1.0,
      "loss_ema": 10.194233683481217,
      "loss_improvement_ema": 0.029154570775031998,
      "grad_norm_ema": 0.0,
      "update_ratio_ema": 0.0,
      "grad_alignment_ema": 0.0,
      "step_fraction": 0.3,
      "mean_update_param_ratio": 1.0008035004138947,
      "max_update_param_ratio": 1.0033522844314575,
      "mean_trust_ratio": 0.7309335321187973
    },
    {
      "step": 7,
      "loss": 9.103510856628418,
      "grad_norm": 2.5621286422710474,
      "gate_value": 1.0,
      "update_multiplier": 1.0,
      "trust_ratio_mix": 1.0,
      "clip_threshold": null,
      "beta2_override": null,
      "orthogonal_mix": 1.0,
      "loss_ema": 10.085161400795936,
      "loss_improvement_ema": 0.03714634196605688,
      "grad_norm_ema": 0.0,
      "update_ratio_ema": 0.0,
      "grad_alignment_ema": 0.0,
      "step_fraction": 0.35,
      "mean_update_param_ratio": 1.0002019107341766,
      "max_update_param_ratio": 1.0019994974136353,
      "mean_trust_ratio": 0.732223391532898
    },
    {
      "step": 8,
      "loss": 8.908967971801758,
      "grad_norm": 8.426915005757733,
      "gate_value": 1.0,
      "update_multiplier": 1.0,
      "trust_ratio_mix": 1.0,
      "clip_threshold": null,
      "beta2_override": null,
      "orthogonal_mix": 1.0,
      "loss_ema": 9.96754205789652,
      "loss_improvement_ema": 0.04519364205939287,
      "grad_norm_ema": 0.0,
      "update_ratio_ema": 0.0,
      "grad_alignment_ema": 0.0,
      "step_fraction": 0.4,
      "mean_update_param_ratio": 0.999445304274559,
      "max_update_param_ratio": 1.0007598400115967,
      "mean_trust_ratio": 0.7492797374725342
    },
    {
      "step": 9,
      "loss": 8.722469329833984,
      "grad_norm": 5.000578419768592,
      "gate_value": 1.0,
      "update_multiplier": 1.0,
      "trust_ratio_mix": 1.0,
      "clip_threshold": null,
      "beta2_override": null,
      "orthogonal_mix": 1.0,
      "loss_ema": 9.843034785090266,
      "loss_improvement_ema": 0.05312500513407893,
      "grad_norm_ema": 0.0,
      "update_ratio_ema": 0.0,
      "grad_alignment_ema": 0.0,
      "step_fraction": 0.45,
      "mean_update_param_ratio": 0.9992367476224899,
      "max_update_param_ratio": 1.0006389617919922,
      "mean_trust_ratio": 0.7435085773468018
    },
    {
      "step": 10,
      "loss": 8.973243713378906,
      "grad_norm": 3.430936917983034,
      "gate_value": 1.0,
      "update_multiplier": 1.0,
      "trust_ratio_mix": 1.0,
      "clip_threshold": null,
      "beta2_override": null,
      "orthogonal_mix": 1.0,
      "loss_ema": 9.756055677919129,
      "loss_improvement_ema": 0.05651041533778476,
      "grad_norm_ema": 0.0,
      "update_ratio_ema": 0.0,
      "grad_alignment_ema": 0.0,
      "step_fraction": 0.5,
      "mean_update_param_ratio": 0.9992744028568268,
      "max_update_param_ratio": 1.0005674362182617,
      "mean_trust_ratio": 0.743261069059372
    },
    {
      "step": 11,
      "loss": 8.284158706665039,
      "grad_norm": 5.468294100953098,
      "gate_value": 1.0,
      "update_multiplier": 1.0,
      "trust_ratio_mix": 1.0,
      "clip_threshold": null,
      "beta2_override": null,
      "orthogonal_mix": 1.0,
      "loss_ema": 9.60886598079372,
      "loss_improvement_ema": 0.06557834351654718,
      "grad_norm_ema": 0.0,
      "update_ratio_ema": 0.0,
      "grad_alignment_ema": 0.0,
      "step_fraction": 0.55,
      "mean_update_param_ratio": 0.9999044090509415,
      "max_update_param_ratio": 1.0023589134216309,
      "mean_trust_ratio": 0.7361047565937042
    },
    {
      "step": 12,
      "loss": 8.508090019226074,
      "grad_norm": 2.9907697887644877,
      "gate_value": 1.0,
      "update_multiplier": 1.0,
      "trust_ratio_mix": 1.0,
      "clip_threshold": null,
      "beta2_override": null,
      "orthogonal_mix": 1.0,
      "loss_ema": 9.498788384636956,
      "loss_improvement_ema": 0.07002826878056881,
      "grad_norm_ema": 0.0,
      "update_ratio_ema": 0.0,
      "grad_alignment_ema": 0.0,
      "step_fraction": 0.6,
      "mean_update_param_ratio": 0.9995651394128799,
      "max_update_param_ratio": 1.0004135370254517,
      "mean_trust_ratio": 0.738867312669754
    },
    {
      "step": 13,
      "loss": 8.127403259277344,
      "grad_norm": 4.175270303783132,
      "gate_value": 1.0,
      "update_multiplier": 1.0,
      "trust_ratio_mix": 1.0,
      "clip_threshold": null,
      "beta2_override": null,
      "orthogonal_mix": 1.0,
      "loss_ema": 9.361649872100996,
      "loss_improvement_ema": 0.07673929315610797,
      "grad_norm_ema": 0.0,
      "update_ratio_ema": 0.0,
      "grad_alignment_ema": 0.0,
      "step_fraction": 0.65,
      "mean_update_param_ratio": 0.9996113926172256,
      "max_update_param_ratio": 1.0003019571304321,
      "mean_trust_ratio": 0.7386372834444046
    },
    {
      "step": 14,
      "loss": 8.039676666259766,
      "grad_norm": 2.818987558512698,
      "gate_value": 1.0,
      "update_multiplier": 1.0,
      "trust_ratio_mix": 1.0,
      "clip_threshold": null,
      "beta2_override": null,
      "orthogonal_mix": 1.0,
      "loss_ema": 9.229452551516871,
      "loss_improvement_ema": 0.0822850958989096,
      "grad_norm_ema": 0.0,
      "update_ratio_ema": 0.0,
      "grad_alignment_ema": 0.0,
      "step_fraction": 0.7,
      "mean_update_param_ratio": 0.9997080266475677,
      "max_update_param_ratio": 1.0002471208572388,
      "mean_trust_ratio": 0.7362481355667114
    },
    {
      "step": 15,
      "loss": 8.282018661499023,
      "grad_norm": 3.0553252406956206,
      "gate_value": 1.0,
      "update_multiplier": 1.0,
      "trust_ratio_mix": 1.0,
      "clip_threshold": null,
      "beta2_override": null,
      "orthogonal_mix": 1.0,
      "loss_ema": 9.134709162515087,
      "loss_improvement_ema": 0.08353092520919711,
      "grad_norm_ema": 0.0,
      "update_ratio_ema": 0.0,
      "grad_alignment_ema": 0.0,
      "step_fraction": 0.75,
      "mean_update_param_ratio": 0.9997721612453461,
      "max_update_param_ratio": 1.0002199411392212,
      "mean_trust_ratio": 0.7421220988035202
    },
    {
      "step": 16,
      "loss": 8.26188850402832,
      "grad_norm": 2.313385180619162,
      "gate_value": 1.0,
      "update_multiplier": 1.0,
      "trust_ratio_mix": 1.0,
      "clip_threshold": null,
      "beta2_override": null,
      "orthogonal_mix": 1.0,
      "loss_ema": 9.04742709666641,
      "loss_improvement_ema": 0.083906039273145,
      "grad_norm_ema": 0.0,
      "update_ratio_ema": 0.0,
      "grad_alignment_ema": 0.0,
      "step_fraction": 0.8,
      "mean_update_param_ratio": 0.9998545497655869,
      "max_update_param_ratio": 1.0001510381698608,
      "mean_trust_ratio": 0.7489029765129089
    },
    {
      "step": 17,
      "loss": 8.01870346069336,
      "grad_norm": 2.7537194545488513,
      "gate_value": 1.0,
      "update_multiplier": 1.0,
      "trust_ratio_mix": 1.0,
      "clip_threshold": null,
      "beta2_override": null,
      "orthogonal_mix": 1.0,
      "loss_ema": 8.944554733069106,
      "loss_improvement_ema": 0.08580267170556097,
      "grad_norm_ema": 0.0,
      "update_ratio_ema": 0.0,
      "grad_alignment_ema": 0.0,
      "step_fraction": 0.85,
      "mean_update_param_ratio": 0.9999401569366455,
      "max_update_param_ratio": 1.0000900030136108,
      "mean_trust_ratio": 0.7394335120916367
    },
    {
      "step": 18,
      "loss": 8.21501350402832,
      "grad_norm": 2.6108642611850232,
      "gate_value": 1.0,
      "update_multiplier": 1.0,
      "trust_ratio_mix": 1.0,
      "clip_threshold": null,
      "beta2_override": null,
      "orthogonal_mix": 1.0,
      "loss_ema": 8.871600610165027,
      "loss_improvement_ema": 0.08451781682541278,
      "grad_norm_ema": 0.0,
      "update_ratio_ema": 0.0,
      "grad_alignment_ema": 0.0,
      "step_fraction": 0.9,
      "mean_update_param_ratio": 0.999972864985466,
      "max_update_param_ratio": 1.0000444650650024,
      "mean_trust_ratio": 0.7415035963058472
    },
    {
      "step": 19,
      "loss": 8.060920715332031,
      "grad_norm": 3.813253062464662,
      "gate_value": 1.0,
      "update_multiplier": 1.0,
      "trust_ratio_mix": 1.0,
      "clip_threshold": null,
      "beta2_override": null,
      "orthogonal_mix": 1.0,
      "loss_ema": 8.790532620681727,
      "loss_improvement_ema": 0.08417283409120146,
      "grad_norm_ema": 0.0,
      "update_ratio_ema": 0.0,
      "grad_alignment_ema": 0.0,
      "step_fraction": 0.95,
      "mean_update_param_ratio": 1.0000000596046448,
      "max_update_param_ratio": 1.0000195503234863,
      "mean_trust_ratio": 0.7427395880222321
    },
    {
      "step": 20,
      "loss": 8.176617622375488,
      "grad_norm": 2.80713979511019,
      "gate_value": 1.0,
      "update_multiplier": 1.0,
      "trust_ratio_mix": 1.0,
      "clip_threshold": null,
      "beta2_override": null,
      "orthogonal_mix": 1.0,
      "loss_ema": 8.729141120851104,
      "loss_improvement_ema": 0.08189470066514368,
      "grad_norm_ema": 0.0,
      "update_ratio_ema": 0.0,
      "grad_alignment_ema": 0.0,
      "step_fraction": 1.0,
      "mean_update_param_ratio": 0.9999999850988388,
      "max_update_param_ratio": 1.0000001192092896,
      "mean_trust_ratio": 0.7352212816476822
    }
  ]
}