{
  "mutation": "H504_beta2_phase2",
  "features": [
    "H504"
  ],
  "valid": true,
  "failure_type": null,
  "final_validation_bpb": 1.4724541096511625,
  "best_validation_bpb": 1.4724541096511625,
  "mean_step_time_ms": 27.559479947686487,
  "total_time_s": 564.7519757070113,
  "steps_completed": 20000,
  "curve": [
    {
      "step": 0,
      "val_bpb": 3.0134784160965746
    },
    {
      "step": 250,
      "val_bpb": 1.981474476803465
    },
    {
      "step": 500,
      "val_bpb": 1.8706850306360023
    },
    {
      "step": 750,
      "val_bpb": 1.8574713030559484
    },
    {
      "step": 1000,
      "val_bpb": 1.8478655122419707
    },
    {
      "step": 1250,
      "val_bpb": 1.8211541374047793
    },
    {
      "step": 1500,
      "val_bpb": 1.8489946796533636
    },
    {
      "step": 1750,
      "val_bpb": 1.757901364127972
    },
    {
      "step": 2000,
      "val_bpb": 1.7818183073608032
    },
    {
      "step": 2250,
      "val_bpb": 1.7791229017307724
    },
    {
      "step": 2500,
      "val_bpb": 1.7397840873423644
    },
    {
      "step": 2750,
      "val_bpb": 1.7301872495616821
    },
    {
      "step": 3000,
      "val_bpb": 1.7070770288895853
    },
    {
      "step": 3250,
      "val_bpb": 1.7222083334191165
    },
    {
      "step": 3500,
      "val_bpb": 1.7123297463936644
    },
    {
      "step": 3750,
      "val_bpb": 1.704817066242564
    },
    {
      "step": 4000,
      "val_bpb": 1.6839868847163935
    },
    {
      "step": 4250,
      "val_bpb": 1.6929947214278462
    },
    {
      "step": 4500,
      "val_bpb": 1.70957709561135
    },
    {
      "step": 4750,
      "val_bpb": 1.6743044505113251
    },
    {
      "step": 5000,
      "val_bpb": 1.6739864821773145
    },
    {
      "step": 5250,
      "val_bpb": 1.6828406251505275
    },
    {
      "step": 5500,
      "val_bpb": 1.6832071569075653
    },
    {
      "step": 5750,
      "val_bpb": 1.6646652893005187
    },
    {
      "step": 6000,
      "val_bpb": 1.6652077617270156
    },
    {
      "step": 6250,
      "val_bpb": 1.6784734440305873
    },
    {
      "step": 6500,
      "val_bpb": 1.671071184623465
    },
    {
      "step": 6750,
      "val_bpb": 1.661232750595823
    },
    {
      "step": 7000,
      "val_bpb": 1.660184567440149
    },
    {
      "step": 7250,
      "val_bpb": 1.6588855637001803
    },
    {
      "step": 7500,
      "val_bpb": 1.6639717005241548
    },
    {
      "step": 7750,
      "val_bpb": 1.6696331375633766
    },
    {
      "step": 8000,
      "val_bpb": 1.671746731681218
    },
    {
      "step": 8250,
      "val_bpb": 1.6453613286471955
    },
    {
      "step": 8500,
      "val_bpb": 1.6565870758795844
    },
    {
      "step": 8750,
      "val_bpb": 1.6591807424948932
    },
    {
      "step": 9000,
      "val_bpb": 1.6388722786362164
    },
    {
      "step": 9250,
      "val_bpb": 1.6512982749382838
    },
    {
      "step": 9500,
      "val_bpb": 1.6659310582956781
    },
    {
      "step": 9750,
      "val_bpb": 1.6788070123468553
    },
    {
      "step": 10000,
      "val_bpb": 1.6742362175454517
    },
    {
      "step": 10250,
      "val_bpb": 1.6622245025113318
    },
    {
      "step": 10500,
      "val_bpb": 1.6516957353557973
    },
    {
      "step": 10750,
      "val_bpb": 1.6286801997934015
    },
    {
      "step": 11000,
      "val_bpb": 1.621005551130864
    },
    {
      "step": 11250,
      "val_bpb": 1.6348526379905661
    },
    {
      "step": 11500,
      "val_bpb": 1.6291605435949084
    },
    {
      "step": 11750,
      "val_bpb": 1.6238102922887159
    },
    {
      "step": 12000,
      "val_bpb": 1.6251868889839123
    },
    {
      "step": 12250,
      "val_bpb": 1.614345308271113
    },
    {
      "step": 12500,
      "val_bpb": 1.6235680177816583
    },
    {
      "step": 12750,
      "val_bpb": 1.6128117621892057
    },
    {
      "step": 13000,
      "val_bpb": 1.6008623114320955
    },
    {
      "step": 13250,
      "val_bpb": 1.5901409184086877
    },
    {
      "step": 13500,
      "val_bpb": 1.5989962822500772
    },
    {
      "step": 13750,
      "val_bpb": 1.5879745556552105
    },
    {
      "step": 14000,
      "val_bpb": 1.5799914343000363
    },
    {
      "step": 14250,
      "val_bpb": 1.576153567360689
    },
    {
      "step": 14500,
      "val_bpb": 1.565687200134184
    },
    {
      "step": 14750,
      "val_bpb": 1.5595025532552527
    },
    {
      "step": 15000,
      "val_bpb": 1.5686902645447336
    },
    {
      "step": 15250,
      "val_bpb": 1.5560259276441777
    },
    {
      "step": 15500,
      "val_bpb": 1.5660297214837475
    },
    {
      "step": 15750,
      "val_bpb": 1.5648716601921735
    },
    {
      "step": 16000,
      "val_bpb": 1.5604005696251975
    },
    {
      "step": 16250,
      "val_bpb": 1.564914254926337
    },
    {
      "step": 16500,
      "val_bpb": 1.5515875292139323
    },
    {
      "step": 16750,
      "val_bpb": 1.5440801394915975
    },
    {
      "step": 17000,
      "val_bpb": 1.5364975985503881
    },
    {
      "step": 17250,
      "val_bpb": 1.540179465667162
    },
    {
      "step": 17500,
      "val_bpb": 1.5285006406892117
    },
    {
      "step": 17750,
      "val_bpb": 1.519771840182136
    },
    {
      "step": 18000,
      "val_bpb": 1.519937199994064
    },
    {
      "step": 18250,
      "val_bpb": 1.5210563291560044
    },
    {
      "step": 18500,
      "val_bpb": 1.5136795723285723
    },
    {
      "step": 18750,
      "val_bpb": 1.5019803995476777
    },
    {
      "step": 19000,
      "val_bpb": 1.4988293387837128
    },
    {
      "step": 19250,
      "val_bpb": 1.4879577789745755
    },
    {
      "step": 19500,
      "val_bpb": 1.4817972781551383
    },
    {
      "step": 19750,
      "val_bpb": 1.4734641745893209
    },
    {
      "step": 20000,
      "val_bpb": 1.4724541096511625
    }
  ],
  "train_curve": [
    {
      "step": 0,
      "train_bpb": 15.323497343698662,
      "step_time_ms": 436.0992980073206
    },
    {
      "step": 500,
      "train_bpb": 9.27179521477867,
      "step_time_ms": 27.65403300873004
    },
    {
      "step": 1000,
      "train_bpb": 9.517528841845674,
      "step_time_ms": 27.57923401077278
    },
    {
      "step": 1500,
      "train_bpb": 9.194790326820149,
      "step_time_ms": 27.96119198319502
    },
    {
      "step": 2000,
      "train_bpb": 9.202652685686994,
      "step_time_ms": 27.669995004544035
    },
    {
      "step": 2500,
      "train_bpb": 8.682352196170532,
      "step_time_ms": 27.695194992702454
    },
    {
      "step": 3000,
      "train_bpb": 8.468373445758836,
      "step_time_ms": 27.583774004597217
    },
    {
      "step": 3500,
      "train_bpb": 8.80613086171891,
      "step_time_ms": 27.877677988726646
    },
    {
      "step": 4000,
      "train_bpb": 8.479801348943367,
      "step_time_ms": 27.937934995861724
    },
    {
      "step": 4500,
      "train_bpb": 8.464004398496316,
      "step_time_ms": 27.561141992919147
    },
    {
      "step": 5000,
      "train_bpb": 8.527728098224607,
      "step_time_ms": 27.756203984608874
    },
    {
      "step": 5500,
      "train_bpb": 8.587772057155039,
      "step_time_ms": 27.73779700510204
    },
    {
      "step": 6000,
      "train_bpb": 8.608415478703403,
      "step_time_ms": 27.53968199249357
    },
    {
      "step": 6500,
      "train_bpb": 8.145283398194946,
      "step_time_ms": 27.722806989913806
    },
    {
      "step": 7000,
      "train_bpb": 8.820514114775866,
      "step_time_ms": 27.484051999635994
    },
    {
      "step": 7500,
      "train_bpb": 8.817382654668958,
      "step_time_ms": 27.684408996719867
    },
    {
      "step": 8000,
      "train_bpb": 8.09109097697747,
      "step_time_ms": 27.721099992049858
    },
    {
      "step": 8500,
      "train_bpb": 8.780194502107591,
      "step_time_ms": 27.553594001801684
    },
    {
      "step": 9000,
      "train_bpb": 8.339108533647934,
      "step_time_ms": 27.60754301561974
    },
    {
      "step": 9500,
      "train_bpb": 8.55314300643851,
      "step_time_ms": 27.51334899221547
    },
    {
      "step": 10000,
      "train_bpb": 8.779821643720519,
      "step_time_ms": 27.796384994871914
    },
    {
      "step": 10500,
      "train_bpb": 7.578868856537337,
      "step_time_ms": 27.483162994030863
    },
    {
      "step": 11000,
      "train_bpb": 7.805514473150381,
      "step_time_ms": 28.70987099595368
    },
    {
      "step": 11500,
      "train_bpb": 9.124495513967691,
      "step_time_ms": 27.835221000714228
    },
    {
      "step": 12000,
      "train_bpb": 8.224242009067268,
      "step_time_ms": 27.567707002162933
    },
    {
      "step": 12500,
      "train_bpb": 7.29482575002534,
      "step_time_ms": 27.59927199804224
    },
    {
      "step": 13000,
      "train_bpb": 7.585739907404608,
      "step_time_ms": 27.5805709825363
    },
    {
      "step": 13500,
      "train_bpb": 8.267399335474781,
      "step_time_ms": 27.903882000828162
    },
    {
      "step": 14000,
      "train_bpb": 8.277927425429999,
      "step_time_ms": 27.73581800283864
    },
    {
      "step": 14500,
      "train_bpb": 8.12786293152375,
      "step_time_ms": 27.537162008229643
    },
    {
      "step": 15000,
      "train_bpb": 8.030154772054365,
      "step_time_ms": 27.465632010716945
    },
    {
      "step": 15500,
      "train_bpb": 7.856401387818272,
      "step_time_ms": 27.58098198683001
    },
    {
      "step": 16000,
      "train_bpb": 8.157869088585086,
      "step_time_ms": 27.681194012984633
    },
    {
      "step": 16500,
      "train_bpb": 7.734595707240593,
      "step_time_ms": 27.662581007461995
    },
    {
      "step": 17000,
      "train_bpb": 8.566664970379948,
      "step_time_ms": 27.47376897605136
    },
    {
      "step": 17500,
      "train_bpb": 7.345479456218661,
      "step_time_ms": 27.46126800775528
    },
    {
      "step": 18000,
      "train_bpb": 6.990358671827479,
      "step_time_ms": 27.754053997341543
    },
    {
      "step": 18500,
      "train_bpb": 8.020492098798288,
      "step_time_ms": 27.833137020934373
    },
    {
      "step": 19000,
      "train_bpb": 8.072041490637304,
      "step_time_ms": 27.562801988096908
    },
    {
      "step": 19500,
      "train_bpb": 6.836801554247508,
      "step_time_ms": 27.803993987618014
    }
  ],
  "production_baseline": true,
  "baseline_schedules": {
    "lr": "linear_warmdown_50pct",
    "momentum": "warmup_0.85_to_0.95_over_300",
    "weight_decay": "linear_decay_to_0"
  },
  "compound_testing": true
}